{
  "users": [
    {
      "id": "e03685ab-7101-42f2-a591-c98397c7b00c",
      "firstName": "Joseph",
      "lastName": "Christiansen",
      "username": "Joseph Christiansen",
      "email": "Joseph79@hotmail.com",
      "phone": "+39 189 480 8324",
      "avatar": "https://cloudflare-ipfs.com/ipfs/Qmd3W5DuhgHirLHGVixi6V76LhCkZUz6pnFt5AJBiyvHye/avatar/696.jpg",
      "sex": "male"
    },
    {
      "id": "1266a437-3528-4e53-9ba3-eb5aa1c9216c",
      "firstName": "Nathan",
      "lastName": "Heidenreich",
      "username": "Nathan Heidenreich",
      "email": "Nathan.Heidenreich@yahoo.com",
      "phone": "+39 429 991 4679",
      "avatar": "https://cloudflare-ipfs.com/ipfs/Qmd3W5DuhgHirLHGVixi6V76LhCkZUz6pnFt5AJBiyvHye/avatar/138.jpg",
      "sex": "male"
    },
    {
      "id": "e1927d60-34f4-4f00-8f52-695bff7b8bda",
      "firstName": "Clyde",
      "lastName": "Labadie",
      "username": "Clyde Labadie",
      "email": "Clyde.Labadie15@hotmail.com",
      "phone": "+39 135 809 3587",
      "avatar": "https://cloudflare-ipfs.com/ipfs/Qmd3W5DuhgHirLHGVixi6V76LhCkZUz6pnFt5AJBiyvHye/avatar/814.jpg",
      "sex": "male"
    },
    {
      "id": "5e54791d-38fa-4dc9-88f4-98e3cb026e69",
      "firstName": "Antonio",
      "lastName": "Stark",
      "username": "Antonio Stark",
      "email": "Antonio68@hotmail.com",
      "phone": "+39 745 193 4010",
      "avatar": "https://cloudflare-ipfs.com/ipfs/Qmd3W5DuhgHirLHGVixi6V76LhCkZUz6pnFt5AJBiyvHye/avatar/173.jpg",
      "sex": "male"
    },
    {
      "id": "8370e021-cb75-4d9c-acf2-1b403b4bb37d",
      "firstName": "Camille",
      "lastName": "Gislason",
      "username": "Camille Gislason",
      "email": "Camille.Gislason20@gmail.com",
      "phone": "+39 125 583 0960",
      "avatar": "https://cloudflare-ipfs.com/ipfs/Qmd3W5DuhgHirLHGVixi6V76LhCkZUz6pnFt5AJBiyvHye/avatar/156.jpg",
      "sex": "female"
    },
    {
      "id": "eaf1daa2-133a-4f64-9398-8ba65f0fa090",
      "firstName": "Walter",
      "lastName": "Jones",
      "username": "Walter Jones",
      "email": "Walter_Jones@gmail.com",
      "phone": "+39 524 970 9533",
      "avatar": "https://cloudflare-ipfs.com/ipfs/Qmd3W5DuhgHirLHGVixi6V76LhCkZUz6pnFt5AJBiyvHye/avatar/203.jpg",
      "sex": "male"
    },
    {
      "id": "e2afb4a3-2109-45f0-9f63-c713d5e37c65",
      "firstName": "Jeannette",
      "lastName": "Kassulke",
      "username": "Jeannette Kassulke",
      "email": "test@test.it",
      "phone": "+39 2345677889",
      "avatar": "https://cloudflare-ipfs.com/ipfs/Qmd3W5DuhgHirLHGVixi6V76LhCkZUz6pnFt5AJBiyvHye/avatar/280.jpg",
      "sex": "female"
    },
    {
      "id": "7e47fa2d-2a2c-49b2-a141-36023b1e41cc",
      "firstName": "Clinton",
      "lastName": "Kassulke",
      "username": "Clinton Kassulke",
      "email": "Clinton.Kassulke19@gmail.com",
      "phone": "+39 348 237 6746",
      "avatar": "https://cloudflare-ipfs.com/ipfs/Qmd3W5DuhgHirLHGVixi6V76LhCkZUz6pnFt5AJBiyvHye/avatar/341.jpg",
      "sex": "male"
    },
    {
      "id": "49560c87-e700-486d-bc87-6e05beada309",
      "firstName": "Tracy",
      "lastName": "Purdy",
      "username": "Tracy Purdy",
      "email": "Tracy27@yahoo.com",
      "phone": "+39 020 102 8935",
      "avatar": "https://cloudflare-ipfs.com/ipfs/Qmd3W5DuhgHirLHGVixi6V76LhCkZUz6pnFt5AJBiyvHye/avatar/1086.jpg",
      "sex": "male"
    },
    {
      "id": "c830407e-4626-421d-8112-50540f8b1c7b",
      "firstName": "Wallace",
      "lastName": "Kirlin",
      "username": "Wallace Kirlin",
      "email": "Wallace.Kirlin24@gmail.com",
      "phone": "+39 981 385 3083",
      "avatar": "https://cloudflare-ipfs.com/ipfs/Qmd3W5DuhgHirLHGVixi6V76LhCkZUz6pnFt5AJBiyvHye/avatar/1089.jpg",
      "sex": "male"
    },
    {
      "id": "c0fb882c-034e-40db-a2ca-be68de590cfc",
      "firstName": "Candice",
      "lastName": "Paucek",
      "username": "Candice Paucek",
      "email": "Candice.Paucek48@yahoo.com",
      "phone": "+39 021 702 3377",
      "avatar": "https://cloudflare-ipfs.com/ipfs/Qmd3W5DuhgHirLHGVixi6V76LhCkZUz6pnFt5AJBiyvHye/avatar/13.jpg",
      "sex": "female"
    },
    {
      "id": "c137bc69-5874-4d93-b4a2-d289b5a234a3",
      "firstName": "Lonnie",
      "lastName": "Lesch",
      "username": "Lonnie Lesch",
      "email": "Lonnie.Lesch@hotmail.com",
      "phone": "+39 857 011 5865",
      "avatar": "https://cloudflare-ipfs.com/ipfs/Qmd3W5DuhgHirLHGVixi6V76LhCkZUz6pnFt5AJBiyvHye/avatar/66.jpg",
      "sex": "male"
    },
    {
      "id": "26663244-43bc-4e6a-8c12-b67ee191ede7",
      "firstName": "Anita",
      "lastName": "Ruecker",
      "username": "Anita Ruecker",
      "email": "Anita_Ruecker83@hotmail.com",
      "phone": "+39 859 603 8583",
      "avatar": "https://cloudflare-ipfs.com/ipfs/Qmd3W5DuhgHirLHGVixi6V76LhCkZUz6pnFt5AJBiyvHye/avatar/1035.jpg",
      "sex": "female"
    },
    {
      "id": "164eb51c-49cf-4dc1-941a-2feec890eb0e",
      "firstName": "Enrique",
      "lastName": "Heaney",
      "username": "Enrique Heaney",
      "email": "Enrique.Heaney@yahoo.com",
      "phone": "+39 422 493 1456",
      "avatar": "https://cloudflare-ipfs.com/ipfs/Qmd3W5DuhgHirLHGVixi6V76LhCkZUz6pnFt5AJBiyvHye/avatar/61.jpg",
      "sex": "male"
    },
    {
      "id": "e5ed0a9c-9113-4c78-aa11-4621aad24969",
      "firstName": "Suzanne",
      "lastName": "Cummerata",
      "username": "Suzanne Cummerata",
      "email": "Suzanne.Cummerata29@hotmail.com",
      "phone": "+39 360 112 4522",
      "avatar": "https://cloudflare-ipfs.com/ipfs/Qmd3W5DuhgHirLHGVixi6V76LhCkZUz6pnFt5AJBiyvHye/avatar/265.jpg",
      "sex": "female"
    },
    {
      "id": "608d570f-2f92-4ee1-8531-9cba4be188b0",
      "firstName": "Mabel",
      "lastName": "Wolff",
      "username": "Mabel Wolff",
      "email": "Mabel20@yahoo.com",
      "phone": "+39 324 039 8670",
      "avatar": "https://cloudflare-ipfs.com/ipfs/Qmd3W5DuhgHirLHGVixi6V76LhCkZUz6pnFt5AJBiyvHye/avatar/922.jpg",
      "sex": "female"
    },
    {
      "id": "eeb9afbe-ddd4-4a84-95d1-2d580ea32868",
      "firstName": "Vivian",
      "lastName": "Little",
      "username": "Vivian Little",
      "email": "Vivian_Little@yahoo.com",
      "phone": "+39 964 202 1905",
      "avatar": "https://cloudflare-ipfs.com/ipfs/Qmd3W5DuhgHirLHGVixi6V76LhCkZUz6pnFt5AJBiyvHye/avatar/708.jpg",
      "sex": "female"
    },
    {
      "id": "01569d6c-4382-4384-9ec8-5cd1a22e8a70",
      "firstName": "Boyd",
      "lastName": "Kohler",
      "username": "Boyd Kohler",
      "email": "Boyd_Kohler@hotmail.com",
      "phone": "+39 486 866 4132",
      "avatar": "https://cloudflare-ipfs.com/ipfs/Qmd3W5DuhgHirLHGVixi6V76LhCkZUz6pnFt5AJBiyvHye/avatar/930.jpg",
      "sex": "male"
    },
    {
      "id": "35e92754-a6d3-41d4-94b4-73fa03cf322a",
      "firstName": "Michele",
      "lastName": "Oberbrunner",
      "username": "Michele Oberbrunner",
      "email": "Michele.Oberbrunner@hotmail.com",
      "phone": "+39 427 284 5127",
      "avatar": "https://cloudflare-ipfs.com/ipfs/Qmd3W5DuhgHirLHGVixi6V76LhCkZUz6pnFt5AJBiyvHye/avatar/483.jpg",
      "sex": "female"
    },
    {
      "id": "1edd506f-2ffc-416f-8ea9-ec4ee70e568f",
      "firstName": "Ismael",
      "lastName": "Jaskolski",
      "username": "Ismael Jaskolski",
      "email": "Ismael.Jaskolski@yahoo.com",
      "phone": "+39 071 476 3937",
      "avatar": "https://cloudflare-ipfs.com/ipfs/Qmd3W5DuhgHirLHGVixi6V76LhCkZUz6pnFt5AJBiyvHye/avatar/604.jpg",
      "sex": "male"
    },
    {
      "id": "62dfe945-3af3-4fdd-9797-998aedbd04f2",
      "firstName": "Tara",
      "lastName": "Greenholt",
      "username": "Tara Greenholt",
      "email": "Tara14@yahoo.com",
      "phone": "+39 458 691 2370",
      "avatar": "https://cloudflare-ipfs.com/ipfs/Qmd3W5DuhgHirLHGVixi6V76LhCkZUz6pnFt5AJBiyvHye/avatar/1008.jpg",
      "sex": "female"
    },
    {
      "id": "79f5692d-04e4-4db5-a680-12e3ac365969",
      "firstName": "Wm",
      "lastName": "Carroll",
      "username": "Wm Carroll",
      "email": "Wm29@yahoo.com",
      "phone": "+39 585 308 7641",
      "avatar": "https://cloudflare-ipfs.com/ipfs/Qmd3W5DuhgHirLHGVixi6V76LhCkZUz6pnFt5AJBiyvHye/avatar/585.jpg",
      "sex": "male"
    },
    {
      "id": "f1c8a28c-9797-4540-93d0-71ba4dba7317",
      "firstName": "Maria",
      "lastName": "McCullough",
      "username": "Maria McCullough",
      "email": "Maria_McCullough90@yahoo.com",
      "phone": "+39 421 937 6549",
      "avatar": "https://cloudflare-ipfs.com/ipfs/Qmd3W5DuhgHirLHGVixi6V76LhCkZUz6pnFt5AJBiyvHye/avatar/378.jpg",
      "sex": "female"
    },
    {
      "id": "88ecd66c-b0be-43de-8a3b-6ea7d8673327",
      "firstName": "Misty",
      "lastName": "Schuppe",
      "username": "Misty Schuppe",
      "email": "Misty23@yahoo.com",
      "phone": "+39 390 219 8045",
      "avatar": "https://cloudflare-ipfs.com/ipfs/Qmd3W5DuhgHirLHGVixi6V76LhCkZUz6pnFt5AJBiyvHye/avatar/884.jpg",
      "sex": "female"
    },
    {
      "id": "66cb3c66-a92f-4534-9c3d-7eb50953d637",
      "firstName": "Tom",
      "lastName": "Mante",
      "username": "Tom Mante",
      "email": "Tom_Mante@hotmail.com",
      "phone": "+39 409 034 9955",
      "avatar": "https://cloudflare-ipfs.com/ipfs/Qmd3W5DuhgHirLHGVixi6V76LhCkZUz6pnFt5AJBiyvHye/avatar/517.jpg",
      "sex": "male"
    },
    {
      "id": "2effc862-2091-433b-b798-c3ad1f3188a7",
      "firstName": "Dallas",
      "lastName": "Cartwright",
      "username": "Dallas Cartwright",
      "email": "Dallas.Cartwright22@hotmail.com",
      "phone": "+39 477 116 2256",
      "avatar": "https://cloudflare-ipfs.com/ipfs/Qmd3W5DuhgHirLHGVixi6V76LhCkZUz6pnFt5AJBiyvHye/avatar/384.jpg",
      "sex": "male"
    },
    {
      "id": "19ecaeaa-1877-4171-a9e0-0ce4a87bf368",
      "firstName": "Claudia",
      "lastName": "Schulist",
      "username": "Claudia Schulist",
      "email": "Claudia48@hotmail.com",
      "phone": "+39 874 689 4760",
      "avatar": "https://cloudflare-ipfs.com/ipfs/Qmd3W5DuhgHirLHGVixi6V76LhCkZUz6pnFt5AJBiyvHye/avatar/608.jpg",
      "sex": "female"
    },
    {
      "id": "79132876-47f2-498d-a7f7-2a1c1e4b171f",
      "firstName": "Amy",
      "lastName": "Langworth",
      "username": "Amy Langworth",
      "email": "Amy_Langworth70@gmail.com",
      "phone": "+39 090 499 9951",
      "avatar": "https://cloudflare-ipfs.com/ipfs/Qmd3W5DuhgHirLHGVixi6V76LhCkZUz6pnFt5AJBiyvHye/avatar/997.jpg",
      "sex": "female"
    },
    {
      "id": "b72da23f-4deb-4714-9263-eed11003e57a",
      "firstName": "Leonard",
      "lastName": "Legros",
      "username": "Leonard Legros",
      "email": "Leonard.Legros@yahoo.com",
      "phone": "+39 781 334 6998",
      "avatar": "https://cloudflare-ipfs.com/ipfs/Qmd3W5DuhgHirLHGVixi6V76LhCkZUz6pnFt5AJBiyvHye/avatar/243.jpg",
      "sex": "male"
    },
    {
      "id": "6ddbed4e-4d94-4dae-a430-bcc1394f963b",
      "firstName": "Shelia",
      "lastName": "Hettinger",
      "username": "Shelia Hettinger",
      "email": "Shelia_Hettinger69@yahoo.com",
      "phone": "+39 726 723 8440",
      "avatar": "https://cloudflare-ipfs.com/ipfs/Qmd3W5DuhgHirLHGVixi6V76LhCkZUz6pnFt5AJBiyvHye/avatar/105.jpg",
      "sex": "female"
    },
    {
      "id": "5b0237d7-d044-45a6-ae45-842a22d7d1c6",
      "firstName": "Alfred",
      "lastName": "Hayes",
      "username": "Alfred Hayes",
      "email": "Alfred1@gmail.com",
      "phone": "+39 557 321 1726",
      "avatar": "https://cloudflare-ipfs.com/ipfs/Qmd3W5DuhgHirLHGVixi6V76LhCkZUz6pnFt5AJBiyvHye/avatar/484.jpg",
      "sex": "male"
    },
    {
      "id": "b543ee1d-85ed-4358-af7a-74f3e94d25b9",
      "firstName": "Wanda",
      "lastName": "Bosco",
      "username": "Wanda Bosco",
      "email": "Wanda1@hotmail.com",
      "phone": "+39 389 736 8683",
      "avatar": "https://cloudflare-ipfs.com/ipfs/Qmd3W5DuhgHirLHGVixi6V76LhCkZUz6pnFt5AJBiyvHye/avatar/469.jpg",
      "sex": "female"
    },
    {
      "id": "f8d045fa-4961-4e79-8f48-fd22b90fc3fd",
      "firstName": "Noel",
      "lastName": "O'Connell",
      "username": "Noel O'Connell",
      "email": "Noel_OConnell@gmail.com",
      "phone": "+39 256 955 0963",
      "avatar": "https://cloudflare-ipfs.com/ipfs/Qmd3W5DuhgHirLHGVixi6V76LhCkZUz6pnFt5AJBiyvHye/avatar/268.jpg",
      "sex": "male"
    },
    {
      "id": "dde8c5c7-5986-4bff-a5ba-4aaa1f62ec71",
      "firstName": "Joshua",
      "lastName": "Dicki",
      "username": "Joshua Dicki",
      "email": "Joshua79@yahoo.com",
      "phone": "+39 376 695 2120",
      "avatar": "https://cloudflare-ipfs.com/ipfs/Qmd3W5DuhgHirLHGVixi6V76LhCkZUz6pnFt5AJBiyvHye/avatar/42.jpg",
      "sex": "male"
    },
    {
      "id": "d67e361e-5fa8-46c9-ba50-4dd5a5e08df3",
      "firstName": "Stephanie",
      "lastName": "Reinger",
      "username": "Stephanie Reinger",
      "email": "Stephanie7@hotmail.com",
      "phone": "+39 933 523 3624",
      "avatar": "https://cloudflare-ipfs.com/ipfs/Qmd3W5DuhgHirLHGVixi6V76LhCkZUz6pnFt5AJBiyvHye/avatar/712.jpg",
      "sex": "female"
    },
    {
      "id": "875cb2d6-e874-452f-bbf8-9ad05b316c8a",
      "firstName": "Kent",
      "lastName": "Emmerich",
      "username": "Kent Emmerich",
      "email": "Kent_Emmerich45@hotmail.com",
      "phone": "+39 879 355 1742",
      "avatar": "https://cloudflare-ipfs.com/ipfs/Qmd3W5DuhgHirLHGVixi6V76LhCkZUz6pnFt5AJBiyvHye/avatar/285.jpg",
      "sex": "male"
    },
    {
      "id": "2a5ab551-0281-4766-b685-24db0bc42bd2",
      "firstName": "Mable",
      "lastName": "Donnelly",
      "username": "Mable Donnelly",
      "email": "Mable32@hotmail.com",
      "phone": "+39 408 275 1858",
      "avatar": "https://cloudflare-ipfs.com/ipfs/Qmd3W5DuhgHirLHGVixi6V76LhCkZUz6pnFt5AJBiyvHye/avatar/1155.jpg",
      "sex": "female"
    },
    {
      "id": "8a122c74-4742-4ad4-95f2-72d246888e58",
      "firstName": "Kurt",
      "lastName": "Bahringer",
      "username": "Kurt Bahringer",
      "email": "Kurt_Bahringer@hotmail.com",
      "phone": "+39 795 306 3064",
      "avatar": "https://cloudflare-ipfs.com/ipfs/Qmd3W5DuhgHirLHGVixi6V76LhCkZUz6pnFt5AJBiyvHye/avatar/857.jpg",
      "sex": "male"
    },
    {
      "id": "472c906c-b4c4-435d-acf4-da8d363b9290",
      "firstName": "Angel",
      "lastName": "Bashirian",
      "username": "Angel Bashirian",
      "email": "Angel_Bashirian@yahoo.com",
      "phone": "+39 922 651 8983",
      "avatar": "https://cloudflare-ipfs.com/ipfs/Qmd3W5DuhgHirLHGVixi6V76LhCkZUz6pnFt5AJBiyvHye/avatar/326.jpg",
      "sex": "male"
    },
    {
      "id": "1671fa85-90ab-4d25-9bf8-bed639242acd",
      "firstName": "Oscar",
      "lastName": "Kemmer",
      "username": "Oscar Kemmer",
      "email": "Oscar12@gmail.com",
      "phone": "+39 757 804 6855",
      "avatar": "https://cloudflare-ipfs.com/ipfs/Qmd3W5DuhgHirLHGVixi6V76LhCkZUz6pnFt5AJBiyvHye/avatar/1003.jpg",
      "sex": "male"
    },
    {
      "id": "38fa0e44-bc53-42f7-919c-b2ec3c0b8c9f",
      "firstName": "Dwayne",
      "lastName": "Turner",
      "username": "Dwayne Turner",
      "email": "Dwayne70@hotmail.com",
      "phone": "+39 198 640 9944",
      "avatar": "https://cloudflare-ipfs.com/ipfs/Qmd3W5DuhgHirLHGVixi6V76LhCkZUz6pnFt5AJBiyvHye/avatar/1212.jpg",
      "sex": "male"
    },
    {
      "id": "8b15365c-71c5-41f7-8203-534517c6ce97",
      "firstName": "Rachel",
      "lastName": "Johns",
      "username": "Rachel Johns",
      "email": "Rachel_Johns@yahoo.com",
      "phone": "+39 856 286 8888",
      "avatar": "https://cloudflare-ipfs.com/ipfs/Qmd3W5DuhgHirLHGVixi6V76LhCkZUz6pnFt5AJBiyvHye/avatar/91.jpg",
      "sex": "female"
    },
    {
      "id": "713618c9-10ce-4ede-800d-dd221559138b",
      "firstName": "Angelina",
      "lastName": "Donnelly",
      "username": "Angelina Donnelly",
      "email": "Angelina_Donnelly98@yahoo.com",
      "phone": "+39 733 286 4757",
      "avatar": "https://cloudflare-ipfs.com/ipfs/Qmd3W5DuhgHirLHGVixi6V76LhCkZUz6pnFt5AJBiyvHye/avatar/204.jpg",
      "sex": "female"
    },
    {
      "id": "b440bbbb-4a83-435e-861f-e49c53810a5b",
      "firstName": "Hilda",
      "lastName": "Pouros",
      "username": "Hilda Pouros",
      "email": "Hilda_Pouros@yahoo.com",
      "phone": "+39 172 391 2194",
      "avatar": "https://cloudflare-ipfs.com/ipfs/Qmd3W5DuhgHirLHGVixi6V76LhCkZUz6pnFt5AJBiyvHye/avatar/1011.jpg",
      "sex": "female"
    },
    {
      "id": "efb5e2e1-48c5-42f9-adb0-a3e69d5aa672",
      "firstName": "Marlon",
      "lastName": "Abernathy",
      "username": "Marlon Abernathy",
      "email": "Marlon84@yahoo.com",
      "phone": "+39 231 947 7310",
      "avatar": "https://cloudflare-ipfs.com/ipfs/Qmd3W5DuhgHirLHGVixi6V76LhCkZUz6pnFt5AJBiyvHye/avatar/736.jpg",
      "sex": "male"
    },
    {
      "id": "cc70c5ca-6b6d-4d6b-9516-996ed04c2e7e",
      "firstName": "Mike",
      "lastName": "Ernser",
      "username": "Mike Ernser",
      "email": "Mike.Ernser90@yahoo.com",
      "phone": "+39 218 475 8764",
      "avatar": "https://cloudflare-ipfs.com/ipfs/Qmd3W5DuhgHirLHGVixi6V76LhCkZUz6pnFt5AJBiyvHye/avatar/1233.jpg",
      "sex": "male"
    },
    {
      "id": "1be6dc09-ecdd-479d-938e-bf1f596bbe4b",
      "firstName": "Tami",
      "lastName": "Batz",
      "username": "Tami Batz",
      "email": "Tami.Batz@hotmail.com",
      "phone": "+39 716 871 0318",
      "avatar": "https://cloudflare-ipfs.com/ipfs/Qmd3W5DuhgHirLHGVixi6V76LhCkZUz6pnFt5AJBiyvHye/avatar/527.jpg",
      "sex": "female"
    },
    {
      "id": "feb9d4f1-83ea-4fbc-8faf-5cb1bf91f4a2",
      "firstName": "Roy",
      "lastName": "Borer",
      "username": "Roy Borer",
      "email": "Roy_Borer@gmail.com",
      "phone": "+39 204 077 3193",
      "avatar": "https://cloudflare-ipfs.com/ipfs/Qmd3W5DuhgHirLHGVixi6V76LhCkZUz6pnFt5AJBiyvHye/avatar/471.jpg",
      "sex": "male"
    },
    {
      "id": "eb28b1d1-ee1c-4825-bad5-bfe607ccebae",
      "firstName": "Devin",
      "lastName": "Kemmer",
      "username": "Devin Kemmer",
      "email": "Devin_Kemmer85@gmail.com",
      "phone": "+39 393 544 9485",
      "avatar": "https://cloudflare-ipfs.com/ipfs/Qmd3W5DuhgHirLHGVixi6V76LhCkZUz6pnFt5AJBiyvHye/avatar/484.jpg",
      "sex": "male"
    },
    {
      "id": "1b336a8f-a26d-4acf-8f95-2dc49ecb0be4",
      "firstName": "Lewis",
      "lastName": "Legros",
      "username": "Lewis Legros",
      "email": "Lewis62@gmail.com",
      "phone": "+39 990 693 5631",
      "avatar": "https://cloudflare-ipfs.com/ipfs/Qmd3W5DuhgHirLHGVixi6V76LhCkZUz6pnFt5AJBiyvHye/avatar/99.jpg",
      "sex": "male"
    },
    {
      "id": "5793ee47-9fe1-4a80-819e-357739a78ce2",
      "firstName": "Lisa",
      "lastName": "Ruecker",
      "username": "Lisa Ruecker",
      "email": "Lisa9@gmail.com",
      "phone": "+39 661 358 0204",
      "avatar": "https://cloudflare-ipfs.com/ipfs/Qmd3W5DuhgHirLHGVixi6V76LhCkZUz6pnFt5AJBiyvHye/avatar/859.jpg",
      "sex": "female"
    },
    {
      "id": "6c1e4068-0a21-4b05-8132-2daab9255722",
      "firstName": "George",
      "lastName": "Steuber",
      "username": "George Steuber",
      "email": "George_Steuber3@hotmail.com",
      "phone": "+39 789 549 1199",
      "avatar": "https://cloudflare-ipfs.com/ipfs/Qmd3W5DuhgHirLHGVixi6V76LhCkZUz6pnFt5AJBiyvHye/avatar/850.jpg",
      "sex": "male"
    },
    {
      "id": "0b7393b4-c2d3-462b-874d-a64d50e341a6",
      "firstName": "Carol",
      "lastName": "Skiles",
      "username": "Carol Skiles",
      "email": "Carol_Skiles@gmail.com",
      "phone": "+39 284 619 4208",
      "avatar": "https://cloudflare-ipfs.com/ipfs/Qmd3W5DuhgHirLHGVixi6V76LhCkZUz6pnFt5AJBiyvHye/avatar/1239.jpg",
      "sex": "female"
    },
    {
      "id": "26f8a6c6-a8be-44c6-9fdc-feac29429311",
      "firstName": "Wilbur",
      "lastName": "Hand",
      "username": "Wilbur Hand",
      "email": "Wilbur.Hand@yahoo.com",
      "phone": "+39 281 809 4400",
      "avatar": "https://cloudflare-ipfs.com/ipfs/Qmd3W5DuhgHirLHGVixi6V76LhCkZUz6pnFt5AJBiyvHye/avatar/182.jpg",
      "sex": "male"
    },
    {
      "id": "7a6af5d5-e4d7-447e-873a-cb97786580a4",
      "firstName": "Johnnie",
      "lastName": "Hudson",
      "username": "Johnnie Hudson",
      "email": "Johnnie_Hudson86@yahoo.com",
      "phone": "+39 511 255 6481",
      "avatar": "https://cloudflare-ipfs.com/ipfs/Qmd3W5DuhgHirLHGVixi6V76LhCkZUz6pnFt5AJBiyvHye/avatar/489.jpg",
      "sex": "male"
    },
    {
      "id": "c4bf8dec-6cab-447c-8c75-0fc806af0d67",
      "firstName": "Bernadette",
      "lastName": "Goldner",
      "username": "Bernadette Goldner",
      "email": "Bernadette.Goldner21@hotmail.com",
      "phone": "+39 212 579 8049",
      "avatar": "https://cloudflare-ipfs.com/ipfs/Qmd3W5DuhgHirLHGVixi6V76LhCkZUz6pnFt5AJBiyvHye/avatar/211.jpg",
      "sex": "female"
    },
    {
      "id": "72c40db2-7a74-4919-95eb-e679d2ad5d8b",
      "firstName": "Antonia",
      "lastName": "Runte",
      "username": "Antonia Runte",
      "email": "Antonia_Runte87@yahoo.com",
      "phone": "+39 561 156 4528",
      "avatar": "https://cloudflare-ipfs.com/ipfs/Qmd3W5DuhgHirLHGVixi6V76LhCkZUz6pnFt5AJBiyvHye/avatar/1237.jpg",
      "sex": "female"
    },
    {
      "id": "77b4a532-df4e-4dc7-8e7f-af879c6378f9",
      "firstName": "Brendan",
      "lastName": "Schuster",
      "username": "Brendan Schuster",
      "email": "Brendan9@yahoo.com",
      "phone": "+39 542 848 1690",
      "avatar": "https://cloudflare-ipfs.com/ipfs/Qmd3W5DuhgHirLHGVixi6V76LhCkZUz6pnFt5AJBiyvHye/avatar/164.jpg",
      "sex": "male"
    },
    {
      "id": "65ac7302-0820-40e1-b16c-7ec5fc7bed66",
      "firstName": "Clint",
      "lastName": "Rolfson",
      "username": "Clint Rolfson",
      "email": "Clint.Rolfson@hotmail.com",
      "phone": "+39 336 452 8918",
      "avatar": "https://cloudflare-ipfs.com/ipfs/Qmd3W5DuhgHirLHGVixi6V76LhCkZUz6pnFt5AJBiyvHye/avatar/1173.jpg",
      "sex": "male"
    },
    {
      "id": "5b647122-b69e-4077-9e15-bee4eae59030",
      "firstName": "Troy",
      "lastName": "Beahan",
      "username": "Troy Beahan",
      "email": "Troy98@gmail.com",
      "phone": "+39 384 703 6812",
      "avatar": "https://cloudflare-ipfs.com/ipfs/Qmd3W5DuhgHirLHGVixi6V76LhCkZUz6pnFt5AJBiyvHye/avatar/448.jpg",
      "sex": "male"
    },
    {
      "id": "70318530-2df4-47b3-9e2b-e4eb9949e18c",
      "firstName": "Alexander",
      "lastName": "Reynolds",
      "username": "Alexander Reynolds",
      "email": "Alexander.Reynolds42@gmail.com",
      "phone": "+39 869 273 7535",
      "avatar": "https://cloudflare-ipfs.com/ipfs/Qmd3W5DuhgHirLHGVixi6V76LhCkZUz6pnFt5AJBiyvHye/avatar/245.jpg",
      "sex": "male"
    },
    {
      "id": "35b8e427-1f14-4092-a0e7-0362ff2886f6",
      "firstName": "Woodrow",
      "lastName": "Simonis",
      "username": "Woodrow Simonis",
      "email": "Woodrow.Simonis87@yahoo.com",
      "phone": "+39 829 990 1614",
      "avatar": "https://cloudflare-ipfs.com/ipfs/Qmd3W5DuhgHirLHGVixi6V76LhCkZUz6pnFt5AJBiyvHye/avatar/348.jpg",
      "sex": "male"
    },
    {
      "id": "59dfdad5-2b86-4b43-bfd3-86e95a7a3816",
      "firstName": "Clifford",
      "lastName": "Jerde",
      "username": "Clifford Jerde",
      "email": "Clifford.Jerde84@yahoo.com",
      "phone": "+39 860 185 1652",
      "avatar": "https://cloudflare-ipfs.com/ipfs/Qmd3W5DuhgHirLHGVixi6V76LhCkZUz6pnFt5AJBiyvHye/avatar/1196.jpg",
      "sex": "male"
    },
    {
      "id": "4d94989d-8571-4c8f-b90b-e4812196f2ad",
      "firstName": "Roxanne",
      "lastName": "Beatty",
      "username": "Roxanne Beatty",
      "email": "Roxanne.Beatty89@yahoo.com",
      "phone": "+39 669 507 7872",
      "avatar": "https://cloudflare-ipfs.com/ipfs/Qmd3W5DuhgHirLHGVixi6V76LhCkZUz6pnFt5AJBiyvHye/avatar/1061.jpg",
      "sex": "female"
    },
    {
      "id": "ef03737b-7f8f-43d1-8ab9-2e4981985300",
      "firstName": "Brenda",
      "lastName": "Schulist",
      "username": "Brenda Schulist",
      "email": "Brenda64@yahoo.com",
      "phone": "+39 076 241 6580",
      "avatar": "https://cloudflare-ipfs.com/ipfs/Qmd3W5DuhgHirLHGVixi6V76LhCkZUz6pnFt5AJBiyvHye/avatar/83.jpg",
      "sex": "female"
    },
    {
      "id": "8c1ca108-b1bc-40e2-b06b-8072141d1337",
      "firstName": "Mona",
      "lastName": "Moen",
      "username": "Mona Moen",
      "email": "Mona27@yahoo.com",
      "phone": "+39 270 435 0984",
      "avatar": "https://cloudflare-ipfs.com/ipfs/Qmd3W5DuhgHirLHGVixi6V76LhCkZUz6pnFt5AJBiyvHye/avatar/249.jpg",
      "sex": "female"
    },
    {
      "id": "1a084bb3-ce95-4c34-94c2-f813cf309127",
      "firstName": "Rodney",
      "lastName": "Abernathy",
      "username": "Rodney Abernathy",
      "email": "Rodney_Abernathy0@yahoo.com",
      "phone": "+39 878 877 4011",
      "avatar": "https://cloudflare-ipfs.com/ipfs/Qmd3W5DuhgHirLHGVixi6V76LhCkZUz6pnFt5AJBiyvHye/avatar/818.jpg",
      "sex": "male"
    },
    {
      "id": "a90b8123-070d-45a4-b40f-1a7aebbb0f74",
      "firstName": "Barry",
      "lastName": "Heller",
      "username": "Barry Heller",
      "email": "Barry.Heller@gmail.com",
      "phone": "+39 472 852 4728",
      "avatar": "https://cloudflare-ipfs.com/ipfs/Qmd3W5DuhgHirLHGVixi6V76LhCkZUz6pnFt5AJBiyvHye/avatar/447.jpg",
      "sex": "male"
    },
    {
      "id": "fc2c2017-f413-40dd-a57c-a9d5308a77f7",
      "firstName": "Devin",
      "lastName": "Hand",
      "username": "Devin Hand",
      "email": "Devin92@gmail.com",
      "phone": "+39 038 783 6482",
      "avatar": "https://cloudflare-ipfs.com/ipfs/Qmd3W5DuhgHirLHGVixi6V76LhCkZUz6pnFt5AJBiyvHye/avatar/949.jpg",
      "sex": "male"
    },
    {
      "id": "71dda7e8-f69b-4def-bc9b-f6389b0d9327",
      "firstName": "Clyde",
      "lastName": "Bartoletti",
      "username": "Clyde Bartoletti",
      "email": "Clyde.Bartoletti40@yahoo.com",
      "phone": "+39 218 778 3731",
      "avatar": "https://cloudflare-ipfs.com/ipfs/Qmd3W5DuhgHirLHGVixi6V76LhCkZUz6pnFt5AJBiyvHye/avatar/659.jpg",
      "sex": "male"
    },
    {
      "id": "496bdc63-fb92-4884-b3fc-6f4afc1b7ec2",
      "firstName": "Sheila",
      "lastName": "Hermann",
      "username": "Sheila Hermann",
      "email": "Sheila.Hermann@gmail.com",
      "phone": "+39 095 648 6605",
      "avatar": "https://cloudflare-ipfs.com/ipfs/Qmd3W5DuhgHirLHGVixi6V76LhCkZUz6pnFt5AJBiyvHye/avatar/236.jpg",
      "sex": "female"
    },
    {
      "id": "61f7c5e1-8e17-48fb-982a-8fb81238fad6",
      "firstName": "Ana",
      "lastName": "Mitchell",
      "username": "Ana Mitchell",
      "email": "Ana_Mitchell@gmail.com",
      "phone": "+39 026 545 7659",
      "avatar": "https://cloudflare-ipfs.com/ipfs/Qmd3W5DuhgHirLHGVixi6V76LhCkZUz6pnFt5AJBiyvHye/avatar/981.jpg",
      "sex": "female"
    },
    {
      "id": "18ffa298-76a3-4781-af2c-deb0c6f0b5eb",
      "firstName": "Marvin",
      "lastName": "Kunde",
      "username": "Marvin Kunde",
      "email": "Marvin_Kunde@hotmail.com",
      "phone": "+39 004 433 0473",
      "avatar": "https://cloudflare-ipfs.com/ipfs/Qmd3W5DuhgHirLHGVixi6V76LhCkZUz6pnFt5AJBiyvHye/avatar/452.jpg",
      "sex": "male"
    },
    {
      "id": "2bdb11bf-720d-430a-a39d-7cfd8a7b824a",
      "firstName": "Florence",
      "lastName": "Hackett",
      "username": "Florence Hackett",
      "email": "Florence_Hackett@hotmail.com",
      "phone": "+39 245 005 9303",
      "avatar": "https://cloudflare-ipfs.com/ipfs/Qmd3W5DuhgHirLHGVixi6V76LhCkZUz6pnFt5AJBiyvHye/avatar/696.jpg",
      "sex": "female"
    },
    {
      "id": "68c2c16b-9505-4f3d-8677-138c5306661a",
      "firstName": "Danny",
      "lastName": "Nikolaus",
      "username": "Danny Nikolaus",
      "email": "Danny.Nikolaus20@yahoo.com",
      "phone": "+39 759 926 1263",
      "avatar": "https://cloudflare-ipfs.com/ipfs/Qmd3W5DuhgHirLHGVixi6V76LhCkZUz6pnFt5AJBiyvHye/avatar/72.jpg",
      "sex": "male"
    },
    {
      "id": "fbf20633-71fd-434a-9b98-95cd1354872e",
      "firstName": "Rosalie",
      "lastName": "Raynor",
      "username": "Rosalie Raynor",
      "email": "Rosalie_Raynor@yahoo.com",
      "phone": "+39 364 961 7457",
      "avatar": "https://cloudflare-ipfs.com/ipfs/Qmd3W5DuhgHirLHGVixi6V76LhCkZUz6pnFt5AJBiyvHye/avatar/1027.jpg",
      "sex": "female"
    },
    {
      "id": "bb38e3c1-5f48-4faa-8819-a90b8ce02429",
      "firstName": "Emilio",
      "lastName": "Conroy",
      "username": "Emilio Conroy",
      "email": "Emilio.Conroy@gmail.com",
      "phone": "+39 778 081 2465",
      "avatar": "https://cloudflare-ipfs.com/ipfs/Qmd3W5DuhgHirLHGVixi6V76LhCkZUz6pnFt5AJBiyvHye/avatar/1130.jpg",
      "sex": "male"
    },
    {
      "id": "61d7ef8f-9f6a-4158-b5d8-a1840dd40870",
      "firstName": "Lionel",
      "lastName": "Langosh",
      "username": "Lionel Langosh",
      "email": "Lionel.Langosh57@hotmail.com",
      "phone": "+39 675 286 1058",
      "avatar": "https://cloudflare-ipfs.com/ipfs/Qmd3W5DuhgHirLHGVixi6V76LhCkZUz6pnFt5AJBiyvHye/avatar/66.jpg",
      "sex": "male"
    },
    {
      "id": "ca70653a-8893-4b17-8703-0efdbee2ac05",
      "firstName": "Irvin",
      "lastName": "Hauck",
      "username": "Irvin Hauck",
      "email": "Irvin.Hauck39@gmail.com",
      "phone": "+39 749 493 2012",
      "avatar": "https://cloudflare-ipfs.com/ipfs/Qmd3W5DuhgHirLHGVixi6V76LhCkZUz6pnFt5AJBiyvHye/avatar/1156.jpg",
      "sex": "male"
    },
    {
      "id": "437dc910-3e25-4ac8-ac0d-2b29442e353c",
      "firstName": "Pablo",
      "lastName": "Walsh",
      "username": "Pablo Walsh",
      "email": "Pablo_Walsh@yahoo.com",
      "phone": "+39 705 421 2207",
      "avatar": "https://cloudflare-ipfs.com/ipfs/Qmd3W5DuhgHirLHGVixi6V76LhCkZUz6pnFt5AJBiyvHye/avatar/879.jpg",
      "sex": "male"
    },
    {
      "id": "9796e85d-8b5a-410b-ac30-647d68681d5e",
      "firstName": "Vicki",
      "lastName": "Kirlin",
      "username": "Vicki Kirlin",
      "email": "Vicki29@gmail.com",
      "phone": "+39 725 548 6375",
      "avatar": "https://cloudflare-ipfs.com/ipfs/Qmd3W5DuhgHirLHGVixi6V76LhCkZUz6pnFt5AJBiyvHye/avatar/423.jpg",
      "sex": "female"
    },
    {
      "id": "2f52ac7c-57e9-46ac-b4eb-ddd3ff10dfd7",
      "firstName": "Wilbert",
      "lastName": "Erdman",
      "username": "Wilbert Erdman",
      "email": "Wilbert41@gmail.com",
      "phone": "+39 178 498 7703",
      "avatar": "https://cloudflare-ipfs.com/ipfs/Qmd3W5DuhgHirLHGVixi6V76LhCkZUz6pnFt5AJBiyvHye/avatar/329.jpg",
      "sex": "male"
    },
    {
      "id": "f453bda4-0d71-4800-ae64-ad5d0c5f64da",
      "firstName": "Ivan",
      "lastName": "Mills",
      "username": "Ivan Mills",
      "email": "Ivan_Mills4@yahoo.com",
      "phone": "+39 510 368 7487",
      "avatar": "https://cloudflare-ipfs.com/ipfs/Qmd3W5DuhgHirLHGVixi6V76LhCkZUz6pnFt5AJBiyvHye/avatar/206.jpg",
      "sex": "male"
    },
    {
      "id": "e792b58c-ae7d-4cea-9668-d303d7c40d43",
      "firstName": "Jeanette",
      "lastName": "West",
      "username": "Jeanette West",
      "email": "Jeanette24@yahoo.com",
      "phone": "+39 668 343 1612",
      "avatar": "https://cloudflare-ipfs.com/ipfs/Qmd3W5DuhgHirLHGVixi6V76LhCkZUz6pnFt5AJBiyvHye/avatar/499.jpg",
      "sex": "female"
    },
    {
      "id": "c5056686-3afd-406a-a55e-84cc48e85501",
      "firstName": "Alex",
      "lastName": "Swift",
      "username": "Alex Swift",
      "email": "Alex95@hotmail.com",
      "phone": "+39 557 965 7129",
      "avatar": "https://cloudflare-ipfs.com/ipfs/Qmd3W5DuhgHirLHGVixi6V76LhCkZUz6pnFt5AJBiyvHye/avatar/761.jpg",
      "sex": "male"
    },
    {
      "id": "f00e65fc-6bfe-41b3-b3be-d856d9d69074",
      "firstName": "Carolyn",
      "lastName": "Herman",
      "username": "Carolyn Herman",
      "email": "Carolyn_Herman@hotmail.com",
      "phone": "+39 607 450 1807",
      "avatar": "https://cloudflare-ipfs.com/ipfs/Qmd3W5DuhgHirLHGVixi6V76LhCkZUz6pnFt5AJBiyvHye/avatar/871.jpg",
      "sex": "female"
    },
    {
      "id": "37229818-4f8d-4a06-bd7d-71de6ee7e176",
      "firstName": "Sean",
      "lastName": "Grant",
      "username": "Sean Grant",
      "email": "Sean_Grant34@gmail.com",
      "phone": "+39 998 046 1916",
      "avatar": "https://cloudflare-ipfs.com/ipfs/Qmd3W5DuhgHirLHGVixi6V76LhCkZUz6pnFt5AJBiyvHye/avatar/1249.jpg",
      "sex": "male"
    },
    {
      "id": "d41aa3a1-c5af-4a83-8850-12a5269469ad",
      "firstName": "Deanna",
      "lastName": "Rice",
      "username": "Deanna Rice",
      "email": "Deanna.Rice@yahoo.com",
      "phone": "+39 846 815 9689",
      "avatar": "https://cloudflare-ipfs.com/ipfs/Qmd3W5DuhgHirLHGVixi6V76LhCkZUz6pnFt5AJBiyvHye/avatar/20.jpg",
      "sex": "female"
    },
    {
      "id": "002a5009-00fa-4be9-b49e-02388715d282",
      "firstName": "Steve",
      "lastName": "Pollich",
      "username": "Steve Pollich",
      "email": "Steve.Pollich@gmail.com",
      "phone": "+39 510 008 2385",
      "avatar": "https://cloudflare-ipfs.com/ipfs/Qmd3W5DuhgHirLHGVixi6V76LhCkZUz6pnFt5AJBiyvHye/avatar/781.jpg",
      "sex": "male"
    },
    {
      "id": "74d7fe14-3956-4e16-9fc2-6ab4dace0a8e",
      "firstName": "Rosemary",
      "lastName": "Borer",
      "username": "Rosemary Borer",
      "email": "Rosemary58@yahoo.com",
      "phone": "+39 702 280 5344",
      "avatar": "https://cloudflare-ipfs.com/ipfs/Qmd3W5DuhgHirLHGVixi6V76LhCkZUz6pnFt5AJBiyvHye/avatar/672.jpg",
      "sex": "female"
    },
    {
      "id": "092685e4-a2ee-44d3-a7a2-c7b177c19db0",
      "firstName": "Roberta",
      "lastName": "Kertzmann",
      "username": "Roberta Kertzmann",
      "email": "Roberta_Kertzmann34@hotmail.com",
      "phone": "+39 312 505 9572",
      "avatar": "https://cloudflare-ipfs.com/ipfs/Qmd3W5DuhgHirLHGVixi6V76LhCkZUz6pnFt5AJBiyvHye/avatar/422.jpg",
      "sex": "female"
    },
    {
      "id": "e33f3410-fe97-4ee4-877b-62ba23fa95b2",
      "firstName": "Jeannie",
      "lastName": "Shanahan",
      "username": "Jeannie Shanahan",
      "email": "Jeannie_Shanahan80@yahoo.com",
      "phone": "+39 127 929 9986",
      "avatar": "https://cloudflare-ipfs.com/ipfs/Qmd3W5DuhgHirLHGVixi6V76LhCkZUz6pnFt5AJBiyvHye/avatar/39.jpg",
      "sex": "female"
    },
    {
      "id": "80144e31-7fd5-4340-a7b0-cb6a685ea0e6",
      "firstName": "Isabel",
      "lastName": "Bailey",
      "username": "Isabel Bailey",
      "email": "Isabel.Bailey13@yahoo.com",
      "phone": "+39 193 268 1808",
      "avatar": "https://cloudflare-ipfs.com/ipfs/Qmd3W5DuhgHirLHGVixi6V76LhCkZUz6pnFt5AJBiyvHye/avatar/271.jpg",
      "sex": "female"
    },
    {
      "id": "40a700ed-a286-41ac-8b01-3caa50c203b4",
      "firstName": "Veronica",
      "lastName": "Muller",
      "username": "Veronica Muller",
      "email": "Veronica93@yahoo.com",
      "phone": "+39 688 358 7915",
      "avatar": "https://cloudflare-ipfs.com/ipfs/Qmd3W5DuhgHirLHGVixi6V76LhCkZUz6pnFt5AJBiyvHye/avatar/96.jpg",
      "sex": "female"
    },
    {
      "id": "911ff66f-a595-4e56-9ced-d5c86bef27dc",
      "firstName": "Misty",
      "lastName": "Oberbrunner",
      "username": "Misty Oberbrunner",
      "email": "Misty_Oberbrunner6@gmail.com",
      "phone": "+39 548 705 7999",
      "avatar": "https://cloudflare-ipfs.com/ipfs/Qmd3W5DuhgHirLHGVixi6V76LhCkZUz6pnFt5AJBiyvHye/avatar/496.jpg",
      "sex": "female"
    },
    {
      "id": "bb741010-6d9d-44b2-a726-a17d82420b95",
      "firstName": "Kristin",
      "lastName": "Glover",
      "username": "Kristin Glover",
      "email": "Kristin44@gmail.com",
      "phone": "+39 474 580 8123",
      "avatar": "https://cloudflare-ipfs.com/ipfs/Qmd3W5DuhgHirLHGVixi6V76LhCkZUz6pnFt5AJBiyvHye/avatar/1179.jpg",
      "sex": "female"
    },
    {
      "id": "85c9ce3b-67b4-462d-aa16-f95e470c056f",
      "firstName": "Santiago",
      "lastName": "Botsford",
      "username": "Santiago Botsford",
      "email": "Santiago67@hotmail.com",
      "phone": "+39 028 667 3980",
      "avatar": "https://cloudflare-ipfs.com/ipfs/Qmd3W5DuhgHirLHGVixi6V76LhCkZUz6pnFt5AJBiyvHye/avatar/1006.jpg",
      "sex": "male"
    },
    {
      "id": "1c35ed30-339c-4613-b018-be34e119aa09",
      "firstName": "Eugene",
      "lastName": "Fisher",
      "username": "Eugene Fisher",
      "email": "Eugene.Fisher35@gmail.com",
      "phone": "+39 197 437 3048",
      "avatar": "https://cloudflare-ipfs.com/ipfs/Qmd3W5DuhgHirLHGVixi6V76LhCkZUz6pnFt5AJBiyvHye/avatar/568.jpg",
      "sex": "male"
    },
    {
      "id": "572199b0-dce3-4f83-a595-96b61586427e",
      "firstName": "Willie",
      "lastName": "Gorczany",
      "username": "Willie Gorczany",
      "email": "Willie_Gorczany33@hotmail.com",
      "phone": "+39 122 529 1831",
      "avatar": "https://cloudflare-ipfs.com/ipfs/Qmd3W5DuhgHirLHGVixi6V76LhCkZUz6pnFt5AJBiyvHye/avatar/979.jpg",
      "sex": "male"
    },
    {
      "id": "61d05ccd-651e-415f-94e6-ac178e52cd69",
      "firstName": "Leslie",
      "lastName": "Russel",
      "username": "Leslie Russel",
      "email": "Leslie.Russel@yahoo.com",
      "phone": "+39 967 229 6518",
      "avatar": "https://cloudflare-ipfs.com/ipfs/Qmd3W5DuhgHirLHGVixi6V76LhCkZUz6pnFt5AJBiyvHye/avatar/901.jpg",
      "sex": "male"
    },
    {
      "id": "54d24a23-7fa6-4257-bee2-7246b20ae491",
      "firstName": "Iris",
      "lastName": "Mraz",
      "username": "Iris Mraz",
      "email": "Iris_Mraz@hotmail.com",
      "phone": "+39 957 102 4898",
      "avatar": "https://cloudflare-ipfs.com/ipfs/Qmd3W5DuhgHirLHGVixi6V76LhCkZUz6pnFt5AJBiyvHye/avatar/1195.jpg",
      "sex": "female"
    },
    {
      "id": "23a96765-e28c-42dc-a1f7-91e01578a428",
      "firstName": "Peggy",
      "lastName": "Mayer",
      "username": "Peggy Mayer",
      "email": "Peggy_Mayer23@yahoo.com",
      "phone": "+39 645 568 2148",
      "avatar": "https://cloudflare-ipfs.com/ipfs/Qmd3W5DuhgHirLHGVixi6V76LhCkZUz6pnFt5AJBiyvHye/avatar/1143.jpg",
      "sex": "female"
    },
    {
      "id": "ab4c8228-bfc4-4449-9df4-26e7ef1f261b",
      "firstName": "Vicky",
      "lastName": "Bogan",
      "username": "Vicky Bogan",
      "email": "Vicky.Bogan@hotmail.com",
      "phone": "+39 234 052 2205",
      "avatar": "https://cloudflare-ipfs.com/ipfs/Qmd3W5DuhgHirLHGVixi6V76LhCkZUz6pnFt5AJBiyvHye/avatar/1046.jpg",
      "sex": "female"
    },
    {
      "id": "bbd96eee-8f19-44da-b4ef-6d5055734ef3",
      "firstName": "Julio",
      "lastName": "Herman",
      "username": "Julio Herman",
      "email": "Julio.Herman@gmail.com",
      "phone": "+39 727 345 0307",
      "avatar": "https://cloudflare-ipfs.com/ipfs/Qmd3W5DuhgHirLHGVixi6V76LhCkZUz6pnFt5AJBiyvHye/avatar/63.jpg",
      "sex": "male"
    },
    {
      "id": "4c96cde6-16bb-4611-9af4-6df61081237c",
      "firstName": "Krystal",
      "lastName": "Waelchi",
      "username": "Krystal Waelchi",
      "email": "Krystal81@gmail.com",
      "phone": "+39 418 295 6644",
      "avatar": "https://cloudflare-ipfs.com/ipfs/Qmd3W5DuhgHirLHGVixi6V76LhCkZUz6pnFt5AJBiyvHye/avatar/474.jpg",
      "sex": "female"
    },
    {
      "id": "44f29a80-89d1-474b-b780-2d8aa66469d8",
      "firstName": "Bernadette",
      "lastName": "Hermann",
      "username": "Bernadette Hermann",
      "email": "Bernadette_Hermann37@hotmail.com",
      "phone": "+39 556 146 7625",
      "avatar": "https://cloudflare-ipfs.com/ipfs/Qmd3W5DuhgHirLHGVixi6V76LhCkZUz6pnFt5AJBiyvHye/avatar/1178.jpg",
      "sex": "female"
    },
    {
      "id": "5c09bd95-59c7-408d-90c2-0dbac18d70c3",
      "firstName": "Howard",
      "lastName": "Dicki",
      "username": "Howard Dicki",
      "email": "Howard_Dicki@gmail.com",
      "phone": "+39 537 624 4367",
      "avatar": "https://cloudflare-ipfs.com/ipfs/Qmd3W5DuhgHirLHGVixi6V76LhCkZUz6pnFt5AJBiyvHye/avatar/158.jpg",
      "sex": "male"
    },
    {
      "id": "07546245-2d60-4690-b677-47efb4f70492",
      "firstName": "Cheryl",
      "lastName": "Champlin",
      "username": "Cheryl Champlin",
      "email": "Cheryl_Champlin@gmail.com",
      "phone": "+39 319 456 3764",
      "avatar": "https://cloudflare-ipfs.com/ipfs/Qmd3W5DuhgHirLHGVixi6V76LhCkZUz6pnFt5AJBiyvHye/avatar/182.jpg",
      "sex": "female"
    },
    {
      "id": "19ad91e1-9169-4a2a-a855-0dd3c9722ebb",
      "firstName": "Nelson",
      "lastName": "Pfannerstill",
      "username": "Nelson Pfannerstill",
      "email": "Nelson.Pfannerstill@hotmail.com",
      "phone": "+39 344 647 8652",
      "avatar": "https://cloudflare-ipfs.com/ipfs/Qmd3W5DuhgHirLHGVixi6V76LhCkZUz6pnFt5AJBiyvHye/avatar/817.jpg",
      "sex": "male"
    },
    {
      "id": "35f8b107-8c27-4412-98be-925255ba9ba2",
      "firstName": "Omar",
      "lastName": "Mueller",
      "username": "Omar Mueller",
      "email": "Omar.Mueller56@yahoo.com",
      "phone": "+39 722 818 4244",
      "avatar": "https://cloudflare-ipfs.com/ipfs/Qmd3W5DuhgHirLHGVixi6V76LhCkZUz6pnFt5AJBiyvHye/avatar/203.jpg",
      "sex": "male"
    },
    {
      "id": "2523151a-410a-489e-8686-fc7e47cfc38f",
      "firstName": "Mercedes",
      "lastName": "Ferry",
      "username": "Mercedes Ferry",
      "email": "Mercedes.Ferry@hotmail.com",
      "phone": "+39 619 648 6455",
      "avatar": "https://cloudflare-ipfs.com/ipfs/Qmd3W5DuhgHirLHGVixi6V76LhCkZUz6pnFt5AJBiyvHye/avatar/304.jpg",
      "sex": "female"
    },
    {
      "id": "19ce151a-f6ed-41df-8744-e4106df34a7d",
      "firstName": "Billy",
      "lastName": "Greenholt",
      "username": "Billy Greenholt",
      "email": "Billy_Greenholt57@gmail.com",
      "phone": "+39 968 916 2689",
      "avatar": "https://cloudflare-ipfs.com/ipfs/Qmd3W5DuhgHirLHGVixi6V76LhCkZUz6pnFt5AJBiyvHye/avatar/306.jpg",
      "sex": "male"
    },
    {
      "id": "a33b9ec5-433e-4015-8fc9-a1b2a7404fe2",
      "firstName": "Elisa",
      "lastName": "Green",
      "username": "Elisa Green",
      "email": "Elisa_Green38@yahoo.com",
      "phone": "+39 110 574 2003",
      "avatar": "https://cloudflare-ipfs.com/ipfs/Qmd3W5DuhgHirLHGVixi6V76LhCkZUz6pnFt5AJBiyvHye/avatar/1126.jpg",
      "sex": "female"
    },
    {
      "id": "e684b7c3-c787-49d0-af70-4a3277bcb809",
      "firstName": "Julia",
      "lastName": "Kling",
      "username": "Julia Kling",
      "email": "Julia_Kling@gmail.com",
      "phone": "+39 871 196 1236",
      "avatar": "https://cloudflare-ipfs.com/ipfs/Qmd3W5DuhgHirLHGVixi6V76LhCkZUz6pnFt5AJBiyvHye/avatar/418.jpg",
      "sex": "female"
    },
    {
      "id": "83d8d34c-1341-4eba-81a9-fef5b5105b5d",
      "firstName": "Matt",
      "lastName": "Harvey",
      "username": "Matt Harvey",
      "email": "Matt.Harvey@yahoo.com",
      "phone": "+39 349 048 0267",
      "avatar": "https://cloudflare-ipfs.com/ipfs/Qmd3W5DuhgHirLHGVixi6V76LhCkZUz6pnFt5AJBiyvHye/avatar/945.jpg",
      "sex": "male"
    },
    {
      "id": "c5997d14-dc83-4340-8bba-d5b2b39e3e0c",
      "firstName": "Dean",
      "lastName": "Rolfson",
      "username": "Dean Rolfson",
      "email": "Dean_Rolfson87@gmail.com",
      "phone": "+39 516 147 3876",
      "avatar": "https://cloudflare-ipfs.com/ipfs/Qmd3W5DuhgHirLHGVixi6V76LhCkZUz6pnFt5AJBiyvHye/avatar/363.jpg",
      "sex": "male"
    },
    {
      "id": "979e7586-20ed-4c29-8bc5-e114e1b3fe88",
      "firstName": "Randolph",
      "lastName": "Breitenberg",
      "username": "Randolph Breitenberg",
      "email": "Randolph21@hotmail.com",
      "phone": "+39 669 542 8097",
      "avatar": "https://cloudflare-ipfs.com/ipfs/Qmd3W5DuhgHirLHGVixi6V76LhCkZUz6pnFt5AJBiyvHye/avatar/500.jpg",
      "sex": "male"
    },
    {
      "id": "e13dab6f-6d09-4abc-b35e-4fc31bbfa462",
      "firstName": "Cody",
      "lastName": "Carroll",
      "username": "Cody Carroll",
      "email": "Cody.Carroll34@yahoo.com",
      "phone": "+39 629 542 0356",
      "avatar": "https://cloudflare-ipfs.com/ipfs/Qmd3W5DuhgHirLHGVixi6V76LhCkZUz6pnFt5AJBiyvHye/avatar/122.jpg",
      "sex": "male"
    },
    {
      "id": "87fc6ed3-eab9-4c8b-b8fe-e91bdd931f75",
      "firstName": "Kristina",
      "lastName": "Connelly",
      "username": "Kristina Connelly",
      "email": "Kristina69@gmail.com",
      "phone": "+39 049 371 0074",
      "avatar": "https://cloudflare-ipfs.com/ipfs/Qmd3W5DuhgHirLHGVixi6V76LhCkZUz6pnFt5AJBiyvHye/avatar/538.jpg",
      "sex": "female"
    },
    {
      "id": "a2ce9943-783f-4a2b-a865-6800085b9278",
      "firstName": "Roberta",
      "lastName": "Johnston",
      "username": "Roberta Johnston",
      "email": "Roberta_Johnston81@hotmail.com",
      "phone": "+39 983 464 7127",
      "avatar": "https://cloudflare-ipfs.com/ipfs/Qmd3W5DuhgHirLHGVixi6V76LhCkZUz6pnFt5AJBiyvHye/avatar/1120.jpg",
      "sex": "female"
    },
    {
      "id": "a612ee22-1246-44ea-95f2-ed327afc85df",
      "firstName": "Iris",
      "lastName": "Schmitt",
      "username": "Iris Schmitt",
      "email": "Iris.Schmitt28@hotmail.com",
      "phone": "+39 976 082 5808",
      "avatar": "https://cloudflare-ipfs.com/ipfs/Qmd3W5DuhgHirLHGVixi6V76LhCkZUz6pnFt5AJBiyvHye/avatar/447.jpg",
      "sex": "female"
    },
    {
      "id": "4c2434d2-ff9a-4885-b839-46e6f0b7269e",
      "firstName": "Forrest",
      "lastName": "Robel",
      "username": "Forrest Robel",
      "email": "Forrest.Robel@gmail.com",
      "phone": "+39 102 919 0146",
      "avatar": "https://cloudflare-ipfs.com/ipfs/Qmd3W5DuhgHirLHGVixi6V76LhCkZUz6pnFt5AJBiyvHye/avatar/530.jpg",
      "sex": "male"
    },
    {
      "id": "997999dd-aacc-4f5d-a62a-57fd1e65090d",
      "firstName": "Lee",
      "lastName": "Marks",
      "username": "Lee Marks",
      "email": "Lee22@hotmail.com",
      "phone": "+39 377 341 5665",
      "avatar": "https://cloudflare-ipfs.com/ipfs/Qmd3W5DuhgHirLHGVixi6V76LhCkZUz6pnFt5AJBiyvHye/avatar/1223.jpg",
      "sex": "female"
    },
    {
      "id": "02cae271-a67f-405e-8038-e9b62d05d1c5",
      "firstName": "Dustin",
      "lastName": "Pollich",
      "username": "Dustin Pollich",
      "email": "Dustin65@yahoo.com",
      "phone": "+39 065 479 4972",
      "avatar": "https://cloudflare-ipfs.com/ipfs/Qmd3W5DuhgHirLHGVixi6V76LhCkZUz6pnFt5AJBiyvHye/avatar/904.jpg",
      "sex": "male"
    },
    {
      "id": "0fc12769-8411-44bf-8e3f-1352c520cb75",
      "firstName": "Austin",
      "lastName": "Ziemann",
      "username": "Austin Ziemann",
      "email": "Austin.Ziemann21@yahoo.com",
      "phone": "+39 633 195 6524",
      "avatar": "https://cloudflare-ipfs.com/ipfs/Qmd3W5DuhgHirLHGVixi6V76LhCkZUz6pnFt5AJBiyvHye/avatar/1157.jpg",
      "sex": "male"
    },
    {
      "id": "17e1a6c1-25a4-400d-983e-2ec9a4206e09",
      "firstName": "Marcos",
      "lastName": "Kuhn",
      "username": "Marcos Kuhn",
      "email": "Marcos91@gmail.com",
      "phone": "+39 375 114 3740",
      "avatar": "https://cloudflare-ipfs.com/ipfs/Qmd3W5DuhgHirLHGVixi6V76LhCkZUz6pnFt5AJBiyvHye/avatar/236.jpg",
      "sex": "male"
    },
    {
      "id": "d54d77c7-6329-4da1-b28c-f1ab75abf317",
      "firstName": "Natalie",
      "lastName": "Kulas",
      "username": "Natalie Kulas",
      "email": "Natalie.Kulas33@yahoo.com",
      "phone": "+39 241 906 4605",
      "avatar": "https://cloudflare-ipfs.com/ipfs/Qmd3W5DuhgHirLHGVixi6V76LhCkZUz6pnFt5AJBiyvHye/avatar/317.jpg",
      "sex": "female"
    },
    {
      "id": "60484341-02e8-4092-8f65-5b078c34f2d2",
      "firstName": "Velma",
      "lastName": "Nicolas",
      "username": "Velma Nicolas",
      "email": "Velma.Nicolas45@yahoo.com",
      "phone": "+39 386 582 6144",
      "avatar": "https://cloudflare-ipfs.com/ipfs/Qmd3W5DuhgHirLHGVixi6V76LhCkZUz6pnFt5AJBiyvHye/avatar/546.jpg",
      "sex": "female"
    },
    {
      "id": "443c9620-7435-476d-8af1-e50c2c9fce3f",
      "firstName": "Lynette",
      "lastName": "Huel",
      "username": "Lynette Huel",
      "email": "Lynette_Huel@hotmail.com",
      "phone": "+39 268 574 7812",
      "avatar": "https://cloudflare-ipfs.com/ipfs/Qmd3W5DuhgHirLHGVixi6V76LhCkZUz6pnFt5AJBiyvHye/avatar/74.jpg",
      "sex": "female"
    },
    {
      "id": "7de16305-deda-4a6e-8081-7442bc09e9c2",
      "firstName": "Alejandro",
      "lastName": "Simonis",
      "username": "Alejandro Simonis",
      "email": "Alejandro_Simonis@gmail.com",
      "phone": "+39 306 081 9934",
      "avatar": "https://cloudflare-ipfs.com/ipfs/Qmd3W5DuhgHirLHGVixi6V76LhCkZUz6pnFt5AJBiyvHye/avatar/844.jpg",
      "sex": "male"
    },
    {
      "id": "a1c4bff1-4b18-4f56-9ba4-10e6ed5c2136",
      "firstName": "Kenny",
      "lastName": "Trantow",
      "username": "Kenny Trantow",
      "email": "Kenny77@yahoo.com",
      "phone": "+39 023 639 8776",
      "avatar": "https://cloudflare-ipfs.com/ipfs/Qmd3W5DuhgHirLHGVixi6V76LhCkZUz6pnFt5AJBiyvHye/avatar/870.jpg",
      "sex": "male"
    },
    {
      "id": "a740b9c7-21eb-452f-9704-154fd82da309",
      "firstName": "Timmy",
      "lastName": "Anderson",
      "username": "Timmy Anderson",
      "email": "Timmy61@hotmail.com",
      "phone": "+39 746 178 3853",
      "avatar": "https://cloudflare-ipfs.com/ipfs/Qmd3W5DuhgHirLHGVixi6V76LhCkZUz6pnFt5AJBiyvHye/avatar/374.jpg",
      "sex": "male"
    },
    {
      "id": "6996c7b8-a55a-419b-a4d5-777ea6b9ebe8",
      "firstName": "Allan",
      "lastName": "MacGyver",
      "username": "Allan MacGyver",
      "email": "Allan_MacGyver26@yahoo.com",
      "phone": "+39 567 149 4797",
      "avatar": "https://cloudflare-ipfs.com/ipfs/Qmd3W5DuhgHirLHGVixi6V76LhCkZUz6pnFt5AJBiyvHye/avatar/383.jpg",
      "sex": "male"
    },
    {
      "id": "c3a8fcbf-e06c-4041-b19b-61d3ff28968c",
      "firstName": "Kristopher",
      "lastName": "Franey",
      "username": "Kristopher Franey",
      "email": "Kristopher93@yahoo.com",
      "phone": "+39 394 575 7312",
      "avatar": "https://cloudflare-ipfs.com/ipfs/Qmd3W5DuhgHirLHGVixi6V76LhCkZUz6pnFt5AJBiyvHye/avatar/660.jpg",
      "sex": "male"
    },
    {
      "id": "5fec65c3-66f0-4ead-b723-4ead741e6472",
      "firstName": "Sandra",
      "lastName": "Thompson",
      "username": "Sandra Thompson",
      "email": "Sandra4@gmail.com",
      "phone": "+39 921 424 4198",
      "avatar": "https://cloudflare-ipfs.com/ipfs/Qmd3W5DuhgHirLHGVixi6V76LhCkZUz6pnFt5AJBiyvHye/avatar/348.jpg",
      "sex": "female"
    },
    {
      "id": "07bb9ce1-9888-4d9f-bed6-8843db81d305",
      "firstName": "Sheila",
      "lastName": "Mertz",
      "username": "Sheila Mertz",
      "email": "Sheila_Mertz20@yahoo.com",
      "phone": "+39 746 561 1269",
      "avatar": "https://cloudflare-ipfs.com/ipfs/Qmd3W5DuhgHirLHGVixi6V76LhCkZUz6pnFt5AJBiyvHye/avatar/329.jpg",
      "sex": "female"
    },
    {
      "id": "92f9ea0a-1f8a-412c-be69-5116ba773316",
      "firstName": "Sharon",
      "lastName": "Feeney",
      "username": "Sharon Feeney",
      "email": "Sharon51@hotmail.com",
      "phone": "+39 989 790 1543",
      "avatar": "https://cloudflare-ipfs.com/ipfs/Qmd3W5DuhgHirLHGVixi6V76LhCkZUz6pnFt5AJBiyvHye/avatar/71.jpg",
      "sex": "female"
    },
    {
      "id": "223eaa81-a8a7-4f67-b92c-7fa414951852",
      "firstName": "Julius",
      "lastName": "Crist",
      "username": "Julius Crist",
      "email": "Julius_Crist89@yahoo.com",
      "phone": "+39 777 790 3251",
      "avatar": "https://cloudflare-ipfs.com/ipfs/Qmd3W5DuhgHirLHGVixi6V76LhCkZUz6pnFt5AJBiyvHye/avatar/483.jpg",
      "sex": "male"
    },
    {
      "id": "17518ec2-1834-4d12-a50f-013bc6099d46",
      "firstName": "Darlene",
      "lastName": "Jacobs",
      "username": "Darlene Jacobs",
      "email": "Darlene96@gmail.com",
      "phone": "+39 236 499 7051",
      "avatar": "https://cloudflare-ipfs.com/ipfs/Qmd3W5DuhgHirLHGVixi6V76LhCkZUz6pnFt5AJBiyvHye/avatar/546.jpg",
      "sex": "female"
    },
    {
      "id": "3cf0111a-8bc7-46b1-b9fc-c327acc08864",
      "firstName": "Alice",
      "lastName": "Larkin",
      "username": "Alice Larkin",
      "email": "Alice_Larkin91@yahoo.com",
      "phone": "+39 855 549 0791",
      "avatar": "https://cloudflare-ipfs.com/ipfs/Qmd3W5DuhgHirLHGVixi6V76LhCkZUz6pnFt5AJBiyvHye/avatar/1157.jpg",
      "sex": "female"
    },
    {
      "id": "6e3e14af-db5d-4b0c-b22b-a8560f6135b5",
      "firstName": "Cheryl",
      "lastName": "Kassulke",
      "username": "Cheryl Kassulke",
      "email": "Cheryl.Kassulke@gmail.com",
      "phone": "+39 785 276 0806",
      "avatar": "https://cloudflare-ipfs.com/ipfs/Qmd3W5DuhgHirLHGVixi6V76LhCkZUz6pnFt5AJBiyvHye/avatar/714.jpg",
      "sex": "female"
    },
    {
      "id": "3d450783-7881-4304-bc85-ff78090298a4",
      "firstName": "Tiffany",
      "lastName": "Kuvalis",
      "username": "Tiffany Kuvalis",
      "email": "Tiffany.Kuvalis@hotmail.com",
      "phone": "+39 280 017 7209",
      "avatar": "https://cloudflare-ipfs.com/ipfs/Qmd3W5DuhgHirLHGVixi6V76LhCkZUz6pnFt5AJBiyvHye/avatar/145.jpg",
      "sex": "female"
    },
    {
      "id": "a5fc41f6-b0af-4f99-a20b-db28489b79c7",
      "firstName": "Kelli",
      "lastName": "Rutherford",
      "username": "Kelli Rutherford",
      "email": "Kelli89@hotmail.com",
      "phone": "+39 519 166 2959",
      "avatar": "https://cloudflare-ipfs.com/ipfs/Qmd3W5DuhgHirLHGVixi6V76LhCkZUz6pnFt5AJBiyvHye/avatar/1037.jpg",
      "sex": "female"
    },
    {
      "id": "f0548cdd-60d3-46e0-a698-e43da0898404",
      "firstName": "Eddie",
      "lastName": "Harvey",
      "username": "Eddie Harvey",
      "email": "Eddie84@yahoo.com",
      "phone": "+39 021 946 7027",
      "avatar": "https://cloudflare-ipfs.com/ipfs/Qmd3W5DuhgHirLHGVixi6V76LhCkZUz6pnFt5AJBiyvHye/avatar/168.jpg",
      "sex": "male"
    },
    {
      "id": "6acecdb1-1501-4043-875e-ace8b91bd463",
      "firstName": "Jean",
      "lastName": "Altenwerth",
      "username": "Jean Altenwerth",
      "email": "Jean82@hotmail.com",
      "phone": "+39 730 369 7430",
      "avatar": "https://cloudflare-ipfs.com/ipfs/Qmd3W5DuhgHirLHGVixi6V76LhCkZUz6pnFt5AJBiyvHye/avatar/1183.jpg",
      "sex": "male"
    },
    {
      "id": "4928654e-bee8-40d9-a48d-456c780b4d6d",
      "firstName": "Alyssa",
      "lastName": "Hilpert",
      "username": "Alyssa Hilpert",
      "email": "Alyssa.Hilpert@gmail.com",
      "phone": "+39 384 818 7728",
      "avatar": "https://cloudflare-ipfs.com/ipfs/Qmd3W5DuhgHirLHGVixi6V76LhCkZUz6pnFt5AJBiyvHye/avatar/938.jpg",
      "sex": "female"
    },
    {
      "id": "7d542c63-80db-476f-907d-1b336d6f766c",
      "firstName": "Cassandra",
      "lastName": "Dare",
      "username": "Cassandra Dare",
      "email": "Cassandra5@yahoo.com",
      "phone": "+39 384 559 7518",
      "avatar": "https://cloudflare-ipfs.com/ipfs/Qmd3W5DuhgHirLHGVixi6V76LhCkZUz6pnFt5AJBiyvHye/avatar/1006.jpg",
      "sex": "female"
    },
    {
      "id": "0cc627cc-ee9a-4dca-a9d5-14618332f0d5",
      "firstName": "Elias",
      "lastName": "Romaguera",
      "username": "Elias Romaguera",
      "email": "Elias.Romaguera@yahoo.com",
      "phone": "+39 285 278 2929",
      "avatar": "https://cloudflare-ipfs.com/ipfs/Qmd3W5DuhgHirLHGVixi6V76LhCkZUz6pnFt5AJBiyvHye/avatar/524.jpg",
      "sex": "male"
    },
    {
      "id": "76ab1c39-84c0-4b1c-98c7-c86427f83dc2",
      "firstName": "Marilyn",
      "lastName": "Heathcote",
      "username": "Marilyn Heathcote",
      "email": "Marilyn_Heathcote@hotmail.com",
      "phone": "+39 238 929 1528",
      "avatar": "https://cloudflare-ipfs.com/ipfs/Qmd3W5DuhgHirLHGVixi6V76LhCkZUz6pnFt5AJBiyvHye/avatar/690.jpg",
      "sex": "female"
    },
    {
      "id": "c2c529f0-f6db-434f-8919-bf53f052846d",
      "firstName": "Ida",
      "lastName": "Bergstrom",
      "username": "Ida Bergstrom",
      "email": "Ida33@gmail.com",
      "phone": "+39 031 544 5804",
      "avatar": "https://cloudflare-ipfs.com/ipfs/Qmd3W5DuhgHirLHGVixi6V76LhCkZUz6pnFt5AJBiyvHye/avatar/1121.jpg",
      "sex": "female"
    },
    {
      "id": "0caaca51-ed7a-4f70-8b48-fab750d8a452",
      "firstName": "Virginia",
      "lastName": "Auer",
      "username": "Virginia Auer",
      "email": "Virginia.Auer30@gmail.com",
      "phone": "+39 176 780 6994",
      "avatar": "https://cloudflare-ipfs.com/ipfs/Qmd3W5DuhgHirLHGVixi6V76LhCkZUz6pnFt5AJBiyvHye/avatar/258.jpg",
      "sex": "female"
    },
    {
      "id": "e68e6dd0-ff98-41af-8ce6-c770df4a083b",
      "firstName": "Vanessa",
      "lastName": "Wisozk",
      "username": "Vanessa Wisozk",
      "email": "Vanessa_Wisozk@yahoo.com",
      "phone": "+39 453 760 6541",
      "avatar": "https://cloudflare-ipfs.com/ipfs/Qmd3W5DuhgHirLHGVixi6V76LhCkZUz6pnFt5AJBiyvHye/avatar/165.jpg",
      "sex": "female"
    },
    {
      "id": "e6448fe8-0867-442d-b213-6b2ddb795f01",
      "firstName": "Carlos",
      "lastName": "Hagenes",
      "username": "Carlos Hagenes",
      "email": "Carlos47@gmail.com",
      "phone": "+39 116 991 4543",
      "avatar": "https://cloudflare-ipfs.com/ipfs/Qmd3W5DuhgHirLHGVixi6V76LhCkZUz6pnFt5AJBiyvHye/avatar/795.jpg",
      "sex": "male"
    },
    {
      "id": "bab02901-27d9-4136-9c7c-5a025b962f06",
      "firstName": "Glen",
      "lastName": "Ledner",
      "username": "Glen Ledner",
      "email": "Glen.Ledner74@gmail.com",
      "phone": "+39 764 409 1876",
      "avatar": "https://cloudflare-ipfs.com/ipfs/Qmd3W5DuhgHirLHGVixi6V76LhCkZUz6pnFt5AJBiyvHye/avatar/1114.jpg",
      "sex": "male"
    },
    {
      "id": "a3e98f8d-db26-4b9d-9bbb-10b92eb31e5a",
      "firstName": "Roosevelt",
      "lastName": "Goodwin",
      "username": "Roosevelt Goodwin",
      "email": "Roosevelt_Goodwin9@hotmail.com",
      "phone": "+39 149 516 0797",
      "avatar": "https://cloudflare-ipfs.com/ipfs/Qmd3W5DuhgHirLHGVixi6V76LhCkZUz6pnFt5AJBiyvHye/avatar/794.jpg",
      "sex": "male"
    },
    {
      "id": "6ac4f5f2-8e38-4dfb-9c1f-763496ca33a7",
      "firstName": "Jasmine",
      "lastName": "White",
      "username": "Jasmine White",
      "email": "Jasmine78@gmail.com",
      "phone": "+39 932 451 5577",
      "avatar": "https://cloudflare-ipfs.com/ipfs/Qmd3W5DuhgHirLHGVixi6V76LhCkZUz6pnFt5AJBiyvHye/avatar/233.jpg",
      "sex": "female"
    },
    {
      "id": "c7452e52-461b-424f-aa0c-f9a603de4444",
      "firstName": "Roderick",
      "lastName": "Mosciski",
      "username": "Roderick Mosciski",
      "email": "Roderick_Mosciski91@hotmail.com",
      "phone": "+39 525 737 3810",
      "avatar": "https://cloudflare-ipfs.com/ipfs/Qmd3W5DuhgHirLHGVixi6V76LhCkZUz6pnFt5AJBiyvHye/avatar/442.jpg",
      "sex": "male"
    },
    {
      "id": "fb1bd304-7ea4-44b3-9e35-311fd220a383",
      "firstName": "Linda",
      "lastName": "Hyatt",
      "username": "Linda Hyatt",
      "email": "Linda_Hyatt31@gmail.com",
      "phone": "+39 985 277 9963",
      "avatar": "https://cloudflare-ipfs.com/ipfs/Qmd3W5DuhgHirLHGVixi6V76LhCkZUz6pnFt5AJBiyvHye/avatar/12.jpg",
      "sex": "female"
    },
    {
      "id": "311a6ac3-be6f-4faa-be4f-943b270c08f8",
      "firstName": "Kristy",
      "lastName": "Kuhlman",
      "username": "Kristy Kuhlman",
      "email": "Kristy11@hotmail.com",
      "phone": "+39 202 930 4957",
      "avatar": "https://cloudflare-ipfs.com/ipfs/Qmd3W5DuhgHirLHGVixi6V76LhCkZUz6pnFt5AJBiyvHye/avatar/170.jpg",
      "sex": "female"
    },
    {
      "id": "33b8c950-9421-4c57-b595-6378f4582cec",
      "firstName": "Mathew",
      "lastName": "Johnson",
      "username": "Mathew Johnson",
      "email": "Mathew.Johnson@hotmail.com",
      "phone": "+39 079 607 8608",
      "avatar": "https://cloudflare-ipfs.com/ipfs/Qmd3W5DuhgHirLHGVixi6V76LhCkZUz6pnFt5AJBiyvHye/avatar/221.jpg",
      "sex": "male"
    },
    {
      "id": "ffdc9fa9-395c-477b-a418-fdcd36ba6c72",
      "firstName": "Hugo",
      "lastName": "Collier",
      "username": "Hugo Collier",
      "email": "Hugo.Collier@gmail.com",
      "phone": "+39 299 030 0988",
      "avatar": "https://cloudflare-ipfs.com/ipfs/Qmd3W5DuhgHirLHGVixi6V76LhCkZUz6pnFt5AJBiyvHye/avatar/562.jpg",
      "sex": "male"
    },
    {
      "id": "7c41eaeb-42df-4c02-b9a0-b725536f9683",
      "firstName": "Micheal",
      "lastName": "O'Keefe",
      "username": "Micheal O'Keefe",
      "email": "Micheal_OKeefe17@yahoo.com",
      "phone": "+39 405 969 3622",
      "avatar": "https://cloudflare-ipfs.com/ipfs/Qmd3W5DuhgHirLHGVixi6V76LhCkZUz6pnFt5AJBiyvHye/avatar/1068.jpg",
      "sex": "male"
    },
    {
      "id": "619a594b-d923-4cd0-b6dc-735be0256963",
      "firstName": "Myra",
      "lastName": "Ledner",
      "username": "Myra Ledner",
      "email": "Myra46@gmail.com",
      "phone": "+39 705 569 8769",
      "avatar": "https://cloudflare-ipfs.com/ipfs/Qmd3W5DuhgHirLHGVixi6V76LhCkZUz6pnFt5AJBiyvHye/avatar/561.jpg",
      "sex": "female"
    },
    {
      "id": "ce047ba6-589c-4526-86d8-3248bd3c8ad6",
      "firstName": "Daryl",
      "lastName": "Lesch",
      "username": "Daryl Lesch",
      "email": "Daryl76@hotmail.com",
      "phone": "+39 766 515 4961",
      "avatar": "https://cloudflare-ipfs.com/ipfs/Qmd3W5DuhgHirLHGVixi6V76LhCkZUz6pnFt5AJBiyvHye/avatar/317.jpg",
      "sex": "male"
    },
    {
      "id": "6b5b0a94-af60-47ac-999e-5373cf8d7922",
      "firstName": "Barbara",
      "lastName": "Kassulke",
      "username": "Barbara Kassulke",
      "email": "Barbara79@yahoo.com",
      "phone": "+39 728 700 3257",
      "avatar": "https://cloudflare-ipfs.com/ipfs/Qmd3W5DuhgHirLHGVixi6V76LhCkZUz6pnFt5AJBiyvHye/avatar/223.jpg",
      "sex": "female"
    },
    {
      "id": "afddcaac-835d-450a-baee-cef8a38db72e",
      "firstName": "Carole",
      "lastName": "West",
      "username": "Carole West",
      "email": "Carole.West75@yahoo.com",
      "phone": "+39 329 400 9037",
      "avatar": "https://cloudflare-ipfs.com/ipfs/Qmd3W5DuhgHirLHGVixi6V76LhCkZUz6pnFt5AJBiyvHye/avatar/299.jpg",
      "sex": "female"
    },
    {
      "id": "dd90900a-1d48-4d26-9e0b-516fd2e7a2cf",
      "firstName": "Spencer",
      "lastName": "Bradtke",
      "username": "Spencer Bradtke",
      "email": "Spencer27@yahoo.com",
      "phone": "+39 748 294 9430",
      "avatar": "https://cloudflare-ipfs.com/ipfs/Qmd3W5DuhgHirLHGVixi6V76LhCkZUz6pnFt5AJBiyvHye/avatar/1174.jpg",
      "sex": "male"
    },
    {
      "id": "aab08d61-a900-40b5-adf9-6375dde95b58",
      "firstName": "Manuel",
      "lastName": "Satterfield",
      "username": "Manuel Satterfield",
      "email": "Manuel_Satterfield55@yahoo.com",
      "phone": "+39 938 201 1254",
      "avatar": "https://cloudflare-ipfs.com/ipfs/Qmd3W5DuhgHirLHGVixi6V76LhCkZUz6pnFt5AJBiyvHye/avatar/147.jpg",
      "sex": "male"
    },
    {
      "id": "4f76c4cc-7222-45df-867c-b7cea5022c78",
      "firstName": "Salvatore",
      "lastName": "Davis",
      "username": "Salvatore Davis",
      "email": "Salvatore58@gmail.com",
      "phone": "+39 340 333 2661",
      "avatar": "https://cloudflare-ipfs.com/ipfs/Qmd3W5DuhgHirLHGVixi6V76LhCkZUz6pnFt5AJBiyvHye/avatar/574.jpg",
      "sex": "male"
    },
    {
      "id": "eb739ff8-543e-45ad-a8e8-78d1ef29b122",
      "firstName": "Tyrone",
      "lastName": "Hahn",
      "username": "Tyrone Hahn",
      "email": "Tyrone_Hahn@hotmail.com",
      "phone": "+39 110 961 3450",
      "avatar": "https://cloudflare-ipfs.com/ipfs/Qmd3W5DuhgHirLHGVixi6V76LhCkZUz6pnFt5AJBiyvHye/avatar/447.jpg",
      "sex": "male"
    },
    {
      "id": "b75540ee-0405-4a0e-ad2b-e864d12da9fe",
      "firstName": "Marian",
      "lastName": "Crooks",
      "username": "Marian Crooks",
      "email": "Marian67@yahoo.com",
      "phone": "+39 857 808 5221",
      "avatar": "https://cloudflare-ipfs.com/ipfs/Qmd3W5DuhgHirLHGVixi6V76LhCkZUz6pnFt5AJBiyvHye/avatar/1228.jpg",
      "sex": "female"
    },
    {
      "id": "6e42ce87-6cb5-481a-82ad-13fd431f5540",
      "firstName": "Marcos",
      "lastName": "Bradtke",
      "username": "Marcos Bradtke",
      "email": "Marcos7@yahoo.com",
      "phone": "+39 531 630 3848",
      "avatar": "https://cloudflare-ipfs.com/ipfs/Qmd3W5DuhgHirLHGVixi6V76LhCkZUz6pnFt5AJBiyvHye/avatar/898.jpg",
      "sex": "male"
    },
    {
      "id": "7d8804f7-1726-431d-acc8-bbd9005e6074",
      "firstName": "Elizabeth",
      "lastName": "Breitenberg",
      "username": "Elizabeth Breitenberg",
      "email": "Elizabeth_Breitenberg94@yahoo.com",
      "phone": "+39 580 225 0057",
      "avatar": "https://cloudflare-ipfs.com/ipfs/Qmd3W5DuhgHirLHGVixi6V76LhCkZUz6pnFt5AJBiyvHye/avatar/980.jpg",
      "sex": "female"
    },
    {
      "id": "869f5faf-e972-490f-a098-dd5b5da818c2",
      "firstName": "Jorge",
      "lastName": "Stark",
      "username": "Jorge Stark",
      "email": "Jorge.Stark34@hotmail.com",
      "phone": "+39 645 912 9044",
      "avatar": "https://cloudflare-ipfs.com/ipfs/Qmd3W5DuhgHirLHGVixi6V76LhCkZUz6pnFt5AJBiyvHye/avatar/504.jpg",
      "sex": "male"
    },
    {
      "id": "c085879b-c5e9-4a7a-9d12-25ddcd7a7db3",
      "firstName": "Johnnie",
      "lastName": "Hickle",
      "username": "Johnnie Hickle",
      "email": "Johnnie75@yahoo.com",
      "phone": "+39 555 264 4907",
      "avatar": "https://cloudflare-ipfs.com/ipfs/Qmd3W5DuhgHirLHGVixi6V76LhCkZUz6pnFt5AJBiyvHye/avatar/1002.jpg",
      "sex": "female"
    },
    {
      "id": "b067cee2-6f9c-4714-ace0-53860a27da1e",
      "firstName": "Steven",
      "lastName": "Hilll",
      "username": "Steven Hilll",
      "email": "Steven85@gmail.com",
      "phone": "+39 964 547 8221",
      "avatar": "https://cloudflare-ipfs.com/ipfs/Qmd3W5DuhgHirLHGVixi6V76LhCkZUz6pnFt5AJBiyvHye/avatar/183.jpg",
      "sex": "male"
    },
    {
      "id": "daf98bcc-eada-469f-90d8-eab7106d9d11",
      "firstName": "Doris",
      "lastName": "DuBuque",
      "username": "Doris DuBuque",
      "email": "Doris_DuBuque82@hotmail.com",
      "phone": "+39 929 604 3436",
      "avatar": "https://cloudflare-ipfs.com/ipfs/Qmd3W5DuhgHirLHGVixi6V76LhCkZUz6pnFt5AJBiyvHye/avatar/865.jpg",
      "sex": "female"
    },
    {
      "id": "b9254b53-627f-4d5a-afcf-581ef0cf184c",
      "firstName": "Lester",
      "lastName": "Frami",
      "username": "Lester Frami",
      "email": "Lester_Frami46@yahoo.com",
      "phone": "+39 397 197 6367",
      "avatar": "https://cloudflare-ipfs.com/ipfs/Qmd3W5DuhgHirLHGVixi6V76LhCkZUz6pnFt5AJBiyvHye/avatar/283.jpg",
      "sex": "male"
    },
    {
      "id": "12972f29-5a2c-475d-994a-835a02b44472",
      "firstName": "Bob",
      "lastName": "O'Keefe",
      "username": "Bob O'Keefe",
      "email": "Bob.OKeefe@gmail.com",
      "phone": "+39 487 109 0488",
      "avatar": "https://cloudflare-ipfs.com/ipfs/Qmd3W5DuhgHirLHGVixi6V76LhCkZUz6pnFt5AJBiyvHye/avatar/355.jpg",
      "sex": "male"
    },
    {
      "id": "ea991292-1dfb-485c-a4cc-c686188a05f1",
      "firstName": "Bonnie",
      "lastName": "Ankunding",
      "username": "Bonnie Ankunding",
      "email": "Bonnie_Ankunding@gmail.com",
      "phone": "+39 867 353 7633",
      "avatar": "https://cloudflare-ipfs.com/ipfs/Qmd3W5DuhgHirLHGVixi6V76LhCkZUz6pnFt5AJBiyvHye/avatar/1233.jpg",
      "sex": "female"
    },
    {
      "id": "9c9ca196-f88f-4de0-a50e-105374ca97d6",
      "firstName": "Rebecca",
      "lastName": "Macejkovic",
      "username": "Rebecca Macejkovic",
      "email": "Rebecca59@yahoo.com",
      "phone": "+39 189 301 1861",
      "avatar": "https://cloudflare-ipfs.com/ipfs/Qmd3W5DuhgHirLHGVixi6V76LhCkZUz6pnFt5AJBiyvHye/avatar/773.jpg",
      "sex": "female"
    },
    {
      "id": "6a486216-0e75-4708-abe0-4d2360a312ad",
      "firstName": "Tami",
      "lastName": "Oberbrunner",
      "username": "Tami Oberbrunner",
      "email": "Tami.Oberbrunner33@gmail.com",
      "phone": "+39 352 633 6337",
      "avatar": "https://cloudflare-ipfs.com/ipfs/Qmd3W5DuhgHirLHGVixi6V76LhCkZUz6pnFt5AJBiyvHye/avatar/247.jpg",
      "sex": "female"
    },
    {
      "id": "ddd3099e-564e-4f6a-a456-13e8f66924b3",
      "firstName": "Amos",
      "lastName": "Dicki",
      "username": "Amos Dicki",
      "email": "Amos_Dicki@yahoo.com",
      "phone": "+39 926 089 5295",
      "avatar": "https://cloudflare-ipfs.com/ipfs/Qmd3W5DuhgHirLHGVixi6V76LhCkZUz6pnFt5AJBiyvHye/avatar/550.jpg",
      "sex": "male"
    },
    {
      "id": "355d099b-684b-48b4-b142-439d61b9862d",
      "firstName": "Maurice",
      "lastName": "Leffler",
      "username": "Maurice Leffler",
      "email": "Maurice.Leffler@gmail.com",
      "phone": "+39 566 989 1885",
      "avatar": "https://cloudflare-ipfs.com/ipfs/Qmd3W5DuhgHirLHGVixi6V76LhCkZUz6pnFt5AJBiyvHye/avatar/968.jpg",
      "sex": "male"
    },
    {
      "id": "42d68cbb-dc2d-438c-a206-d3549a663b98",
      "firstName": "Delbert",
      "lastName": "Rau",
      "username": "Delbert Rau",
      "email": "Delbert_Rau@yahoo.com",
      "phone": "+39 920 041 9871",
      "avatar": "https://cloudflare-ipfs.com/ipfs/Qmd3W5DuhgHirLHGVixi6V76LhCkZUz6pnFt5AJBiyvHye/avatar/261.jpg",
      "sex": "male"
    },
    {
      "id": "8176e42d-6eea-4bc0-acd4-e02d296e6b55",
      "firstName": "Genevieve",
      "lastName": "Grant",
      "username": "Genevieve Grant",
      "email": "Genevieve.Grant56@gmail.com",
      "phone": "+39 064 886 0290",
      "avatar": "https://cloudflare-ipfs.com/ipfs/Qmd3W5DuhgHirLHGVixi6V76LhCkZUz6pnFt5AJBiyvHye/avatar/624.jpg",
      "sex": "female"
    },
    {
      "id": "66198137-c332-4aa4-ae5b-9bdb8e29d3c7",
      "firstName": "Lorene",
      "lastName": "Padberg",
      "username": "Lorene Padberg",
      "email": "Lorene_Padberg@gmail.com",
      "phone": "+39 670 373 4239",
      "avatar": "https://cloudflare-ipfs.com/ipfs/Qmd3W5DuhgHirLHGVixi6V76LhCkZUz6pnFt5AJBiyvHye/avatar/124.jpg",
      "sex": "female"
    },
    {
      "id": "79389c8b-209b-473c-975b-e76c17fbf5b5",
      "firstName": "Janet",
      "lastName": "Bruen",
      "username": "Janet Bruen",
      "email": "Janet_Bruen@gmail.com",
      "phone": "+39 370 733 7267",
      "avatar": "https://cloudflare-ipfs.com/ipfs/Qmd3W5DuhgHirLHGVixi6V76LhCkZUz6pnFt5AJBiyvHye/avatar/1090.jpg",
      "sex": "female"
    },
    {
      "id": "cf2300e5-23cc-4d08-8aa5-5d90b52432aa",
      "firstName": "Grace",
      "lastName": "Rowe",
      "username": "Grace Rowe",
      "email": "Grace_Rowe@hotmail.com",
      "phone": "+39 293 330 1437",
      "avatar": "https://cloudflare-ipfs.com/ipfs/Qmd3W5DuhgHirLHGVixi6V76LhCkZUz6pnFt5AJBiyvHye/avatar/534.jpg",
      "sex": "female"
    },
    {
      "id": "56242c9f-56bf-4b76-aee9-35b9e8f20039",
      "firstName": "Pat",
      "lastName": "Feil",
      "username": "Pat Feil",
      "email": "Pat_Feil92@gmail.com",
      "phone": "+39 186 966 4422",
      "avatar": "https://cloudflare-ipfs.com/ipfs/Qmd3W5DuhgHirLHGVixi6V76LhCkZUz6pnFt5AJBiyvHye/avatar/218.jpg",
      "sex": "female"
    },
    {
      "id": "7b9ff927-7582-4abc-91cc-99ef4dcc8a26",
      "firstName": "Julius",
      "lastName": "Gutmann",
      "username": "Julius Gutmann",
      "email": "Julius84@gmail.com",
      "phone": "+39 934 729 7601",
      "avatar": "https://cloudflare-ipfs.com/ipfs/Qmd3W5DuhgHirLHGVixi6V76LhCkZUz6pnFt5AJBiyvHye/avatar/212.jpg",
      "sex": "male"
    },
    {
      "id": "5b010ea7-9152-474d-96b5-038c961b9708",
      "firstName": "Ronnie",
      "lastName": "Ferry",
      "username": "Ronnie Ferry",
      "email": "Ronnie.Ferry@gmail.com",
      "phone": "+39 715 773 7841",
      "avatar": "https://cloudflare-ipfs.com/ipfs/Qmd3W5DuhgHirLHGVixi6V76LhCkZUz6pnFt5AJBiyvHye/avatar/328.jpg",
      "sex": "male"
    },
    {
      "id": "f4b1d950-3d35-4ea9-a9fe-24a24504b614",
      "firstName": "Hannah",
      "lastName": "Jakubowski",
      "username": "Hannah Jakubowski",
      "email": "Hannah.Jakubowski20@hotmail.com",
      "phone": "+39 193 744 1107",
      "avatar": "https://cloudflare-ipfs.com/ipfs/Qmd3W5DuhgHirLHGVixi6V76LhCkZUz6pnFt5AJBiyvHye/avatar/1052.jpg",
      "sex": "female"
    },
    {
      "id": "bfa60817-fadc-4b35-91ad-1d45e05fbae8",
      "firstName": "Angela",
      "lastName": "Hayes",
      "username": "Angela Hayes",
      "email": "Angela_Hayes@hotmail.com",
      "phone": "+39 412 286 6622",
      "avatar": "https://cloudflare-ipfs.com/ipfs/Qmd3W5DuhgHirLHGVixi6V76LhCkZUz6pnFt5AJBiyvHye/avatar/246.jpg",
      "sex": "female"
    }
  ]
}